.hgignore
.hgtags
CHANGES
README
requirements.txt
setup.py
sss/__init__.py
sss/admin.py
sss/exceptions.py
sss/managers.py
sss/models.py
sss/tests.py
sss/views.py
sss.egg-info/PKG-INFO
sss.egg-info/SOURCES.txt
sss.egg-info/dependency_links.txt
sss.egg-info/requires.txt
sss.egg-info/top_level.txt
sss/conf/__init__.py
sss/conf/settings.py
sss/locale/fr/LC_MESSAGES/django.mo
sss/locale/fr/LC_MESSAGES/django.po
sss/templates/admin/sss/backlogitem/change_list.html
sss/templatetags/__init__.py
sss/templatetags/sss_tags.py
sss/templatetags/static/jquery.flot.js