Metadata-Version: 1.0
Name: sss
Version: 1.2
Summary: Simple Scrum System is a basic Django-based Scrum-like project manager. It takes advantage of the automagic admin contrib site.
Home-page: https://bitbucket.org/brunobord/sss/
Author: Bruno Bord
Author-email: bruno@jehaisleprintemps.net
License: WTFPL
Download-URL: http://pypi.python.org/pypi/sss
Keywords: django scrum
Platform: UNKNOWN
Classifier: Development Status :: 3 - Alpha
Classifier: Environment :: Web Environment
Classifier: Intended Audience :: Developers
Classifier: Topic :: Software Development
Classifier: Framework :: Django
Classifier: License :: Freely Distributable
Classifier: Operating System :: OS Independent
